openapi_to_rdf/__init__.py
openapi_to_rdf/main.py
openapi_to_rdf/rdf_converter.py
openapi_to_rdf/shacl_converter.py
openapi_to_rdf-0.1.1.dist-info/LICENSE
openapi_to_rdf-0.1.1.dist-info/METADATA
openapi_to_rdf-0.1.1.dist-info/WHEEL
openapi_to_rdf-0.1.1.dist-info/entry_points.txt
openapi_to_rdf-0.1.1.dist-info/RECORD
