Metadata-Version: 2.3
Name: openapi-to-rdf
Version: 0.1.1
Summary: Convert OpenAPI YAML specifications to RDF vocabularies and SHACL validation shapes for telecom intent-based automation and TMForum standards
License: MIT
Keywords: openapi,rdf,shacl,TMF,TMForum,3gpp,intents,intent-based,telecom,telecommunications,automation,semantic-web,network-management,5g,etsi
Author: Jean Martins
Author-email: jean.martins@gmail.com
Requires-Python: >=3.10,<4.0
Classifier: Development Status :: 3 - Alpha
Classifier: Intended Audience :: Developers
Classifier: Intended Audience :: Science/Research
Classifier: Intended Audience :: Telecommunications Industry
Classifier: License :: OSI Approved :: MIT License
Classifier: Programming Language :: Python :: 3
Classifier: Programming Language :: Python :: 3.10
Classifier: Programming Language :: Python :: 3.11
Classifier: Programming Language :: Python :: 3.12
Classifier: Programming Language :: Python :: 3.13
Classifier: Topic :: Communications
Classifier: Topic :: Internet :: WWW/HTTP :: HTTP Servers
Classifier: Topic :: Scientific/Engineering :: Information Analysis
Classifier: Topic :: Software Development :: Libraries :: Python Modules
Classifier: Topic :: System :: Networking
Requires-Dist: pyyaml (>=6.0.2,<7.0.0)
Requires-Dist: rdflib (>=7.1.3,<8.0.0)
Requires-Dist: requests (>=2.32.5,<3.0.0)
Project-URL: Homepage, https://github.com/EricssonResearch/openapi-to-rdf
Project-URL: Repository, https://github.com/EricssonResearch/openapi-to-rdf
